odoo/addons/data_encryption/README.rst
odoo/addons/data_encryption/__init__.py
odoo/addons/data_encryption/__manifest__.py
odoo/addons/data_encryption/i18n/ca.po
odoo/addons/data_encryption/i18n/data_encryption.pot
odoo/addons/data_encryption/i18n/de.po
odoo/addons/data_encryption/i18n/es.po
odoo/addons/data_encryption/i18n/it.po
odoo/addons/data_encryption/i18n/sv.po
odoo/addons/data_encryption/models/__init__.py
odoo/addons/data_encryption/models/encrypted_data.py
odoo/addons/data_encryption/readme/CONFIGURE.md
odoo/addons/data_encryption/readme/CONTRIBUTORS.md
odoo/addons/data_encryption/readme/DESCRIPTION.md
odoo/addons/data_encryption/readme/ROADMAP.md
odoo/addons/data_encryption/security/ir.model.access.csv
odoo/addons/data_encryption/static/description/icon.png
odoo/addons/data_encryption/static/description/index.html
odoo/addons/data_encryption/tests/__init__.py
odoo/addons/data_encryption/tests/common.py
odoo/addons/data_encryption/tests/test_data_encrypt.py
odoo_addon_data_encryption-18.0.1.0.0.4.dist-info/METADATA
odoo_addon_data_encryption-18.0.1.0.0.4.dist-info/WHEEL
odoo_addon_data_encryption-18.0.1.0.0.4.dist-info/top_level.txt
odoo_addon_data_encryption-18.0.1.0.0.4.dist-info/RECORD
