Metadata-Version: 2.1
Name: odoo-addon-data_encryption
Version: 18.0.1.0.0.4
Requires-Python: >=3.10
Requires-Dist: cryptography
Requires-Dist: odoo==18.0.*
Summary: Store accounts and credentials encrypted by environment
Home-page: https://github.com/OCA/server-env
License: AGPL-3
Author: Akretion, Odoo Community Association (OCA)
Author-email: support@odoo-community.org
Classifier: Programming Language :: Python
Classifier: Framework :: Odoo
Classifier: Framework :: Odoo :: 18.0
Classifier: License :: OSI Approved :: GNU Affero General Public License v3
Classifier: Development Status :: 5 - Production/Stable
